{"nome":"Amalyn Biagini","id":7,"url":"https://www.facebook.com/100002079412785"}
{"nome":"Pablo Sarkis","id":9,"url":"https://www.facebook.com/100002376109505"}
{"nome":"Fabíola Borges","id":10,"url":"https://www.facebook.com/100002922095209"}
{"nome":"Clissiane Gonçalves","id":13,"url":"https://www.facebook.com/1459041931"}
{"nome":"Daurimar Mendes","id":14,"url":"https://www.facebook.com/100003044947434"}
{"nome":"Goreti Lima","id":15,"url":"https://www.facebook.com/100004868524557"}
{"nome":"Suzana Carvalho","id":16,"url":"https://www.facebook.com/100001306571177"}
{"nome":"Emanuelle Rankoski","id":17,"url":"https://www.facebook.com/100001420832063"}
{"nome":"Idomar Augusto Cerutti","id":18,"url":"https://www.facebook.com/100002858779518"}
{"nome":"Projeto Pegaí","id":19,"url":"https://www.facebook.com/678148432200487"}
{"nome":"Henrique Lemes","id":20,"url":"https://www.facebook.com/100002653354256"}
{"nome":"Layla Fran","id":21,"url":"https://www.facebook.com/100001907615215"}
{"nome":"Dierone Foltran","id":22,"url":"https://www.facebook.com/100002929564160"}
